{
  "document": "62 (2016) - Werner.pdf",
  "parser_family": "narrative",
  "page_stats": [
    {
      "page_number": 1,
      "char_count": 688,
      "line_count": 11,
      "numbered_entry_lines": 0,
      "section_headers": 0,
      "probable_ocr_noise": 0.0
    },
    {
      "page_number": 2,
      "char_count": 2037,
      "line_count": 35,
      "numbered_entry_lines": 1,
      "section_headers": 1,
      "probable_ocr_noise": 0.0
    },
    {
      "page_number": 3,
      "char_count": 2775,
      "line_count": 43,
      "numbered_entry_lines": 1,
      "section_headers": 2,
      "probable_ocr_noise": 0.0
    },
    {
      "page_number": 4,
      "char_count": 2710,
      "line_count": 43,
      "numbered_entry_lines": 1,
      "section_headers": 1,
      "probable_ocr_noise": 0.0
    },
    {
      "page_number": 5,
      "char_count": 2607,
      "line_count": 40,
      "numbered_entry_lines": 1,
      "section_headers": 2,
      "probable_ocr_noise": 0.0
    },
    {
      "page_number": 6,
      "char_count": 2833,
      "line_count": 44,
      "numbered_entry_lines": 0,
      "section_headers": 2,
      "probable_ocr_noise": 0.0
    },
    {
      "page_number": 7,
      "char_count": 2535,
      "line_count": 42,
      "numbered_entry_lines": 0,
      "section_headers": 2,
      "probable_ocr_noise": 0.0
    },
    {
      "page_number": 8,
      "char_count": 2681,
      "line_count": 42,
      "numbered_entry_lines": 0,
      "section_headers": 0,
      "probable_ocr_noise": 0.0
    },
    {
      "page_number": 9,
      "char_count": 2982,
      "line_count": 45,
      "numbered_entry_lines": 0,
      "section_headers": 1,
      "probable_ocr_noise": 0.0
    },
    {
      "page_number": 10,
      "char_count": 2740,
      "line_count": 40,
      "numbered_entry_lines": 0,
      "section_headers": 2,
      "probable_ocr_noise": 0.0
    },
    {
      "page_number": 11,
      "char_count": 2868,
      "line_count": 44,
      "numbered_entry_lines": 0,
      "section_headers": 1,
      "probable_ocr_noise": 0.0
    },
    {
      "page_number": 12,
      "char_count": 2775,
      "line_count": 43,
      "numbered_entry_lines": 1,
      "section_headers": 1,
      "probable_ocr_noise": 0.0
    },
    {
      "page_number": 13,
      "char_count": 3220,
      "line_count": 47,
      "numbered_entry_lines": 1,
      "section_headers": 1,
      "probable_ocr_noise": 0.0
    },
    {
      "page_number": 14,
      "char_count": 2929,
      "line_count": 49,
      "numbered_entry_lines": 0,
      "section_headers": 0,
      "probable_ocr_noise": 0.0
    },
    {
      "page_number": 15,
      "char_count": 2809,
      "line_count": 43,
      "numbered_entry_lines": 0,
      "section_headers": 1,
      "probable_ocr_noise": 0.0
    },
    {
      "page_number": 16,
      "char_count": 2815,
      "line_count": 43,
      "numbered_entry_lines": 0,
      "section_headers": 1,
      "probable_ocr_noise": 0.0
    },
    {
      "page_number": 17,
      "char_count": 3143,
      "line_count": 45,
      "numbered_entry_lines": 1,
      "section_headers": 0,
      "probable_ocr_noise": 0.0
    },
    {
      "page_number": 18,
      "char_count": 2454,
      "line_count": 39,
      "numbered_entry_lines": 0,
      "section_headers": 3,
      "probable_ocr_noise": 0.0
    },
    {
      "page_number": 19,
      "char_count": 2509,
      "line_count": 40,
      "numbered_entry_lines": 0,
      "section_headers": 2,
      "probable_ocr_noise": 0.0
    },
    {
      "page_number": 20,
      "char_count": 1320,
      "line_count": 19,
      "numbered_entry_lines": 0,
      "section_headers": 1,
      "probable_ocr_noise": 0.0
    },
    {
      "page_number": 21,
      "char_count": 72,
      "line_count": 1,
      "numbered_entry_lines": 0,
      "section_headers": 0,
      "probable_ocr_noise": 0.0
    }
  ],
  "detected_sections": [
    "AENEID: GENERAL",
    "ANCIENT AUTHORS AFTER VERGIL",
    "ANCIENT COMMENTARIES, SCHOLIA, VITAE",
    "APPENDIX VERGILIANA",
    "CHARACTERS",
    "COMPANIONS, COLLECTIONS, AND GENERAL",
    "ECLOGUES: GENERAL",
    "ECLOGUES: INDIVIDUAL POEMS",
    "FURTHER BIBLIOGRAPHY",
    "GEORGICS: GENERAL",
    "GEORGICS: INDIVIDUAL POEMS",
    "HISTORY, MATERIAL CULTURE, AND LANDSCAPE",
    "MANUSCRIPTS, TEXTUAL TRADITION",
    "PHILOSOPHY AND RELIGION",
    "RENAISSANCE AND TUDOR WRITERS",
    "STUDIES",
    "STYLE, LANGUAGE, AND METER",
    "THE MIDDLE AGES",
    "TRANSLATIONS, COMMENTARIES, EDITIONS",
    "TWENTIETH CENTURY",
    "TWENTY-FIRST CENTURY",
    "VERGIL AND AUGUSTAN WRITERS",
    "VERGIL AND EARLIER WRITERS",
    "VERGIL AND THE ARTS"
  ]
}