{
  "document": "63 (2017) - Werner.pdf",
  "parser_family": "narrative",
  "page_stats": [
    {
      "page_number": 1,
      "char_count": 687,
      "line_count": 9,
      "numbered_entry_lines": 0,
      "section_headers": 0,
      "probable_ocr_noise": 0.0
    },
    {
      "page_number": 2,
      "char_count": 1962,
      "line_count": 35,
      "numbered_entry_lines": 1,
      "section_headers": 1,
      "probable_ocr_noise": 0.0
    },
    {
      "page_number": 3,
      "char_count": 2610,
      "line_count": 43,
      "numbered_entry_lines": 0,
      "section_headers": 2,
      "probable_ocr_noise": 0.0
    },
    {
      "page_number": 4,
      "char_count": 2261,
      "line_count": 34,
      "numbered_entry_lines": 0,
      "section_headers": 2,
      "probable_ocr_noise": 0.0004422821760283061
    },
    {
      "page_number": 5,
      "char_count": 2493,
      "line_count": 48,
      "numbered_entry_lines": 0,
      "section_headers": 3,
      "probable_ocr_noise": 0.0
    },
    {
      "page_number": 6,
      "char_count": 2623,
      "line_count": 41,
      "numbered_entry_lines": 0,
      "section_headers": 0,
      "probable_ocr_noise": 0.0
    },
    {
      "page_number": 7,
      "char_count": 2827,
      "line_count": 43,
      "numbered_entry_lines": 0,
      "section_headers": 1,
      "probable_ocr_noise": 0.0
    },
    {
      "page_number": 8,
      "char_count": 2671,
      "line_count": 43,
      "numbered_entry_lines": 0,
      "section_headers": 1,
      "probable_ocr_noise": 0.0
    },
    {
      "page_number": 9,
      "char_count": 2812,
      "line_count": 43,
      "numbered_entry_lines": 1,
      "section_headers": 1,
      "probable_ocr_noise": 0.0
    },
    {
      "page_number": 10,
      "char_count": 3014,
      "line_count": 43,
      "numbered_entry_lines": 0,
      "section_headers": 1,
      "probable_ocr_noise": 0.0
    },
    {
      "page_number": 11,
      "char_count": 2950,
      "line_count": 44,
      "numbered_entry_lines": 0,
      "section_headers": 1,
      "probable_ocr_noise": 0.0
    },
    {
      "page_number": 12,
      "char_count": 2902,
      "line_count": 43,
      "numbered_entry_lines": 0,
      "section_headers": 1,
      "probable_ocr_noise": 0.0
    },
    {
      "page_number": 13,
      "char_count": 2885,
      "line_count": 47,
      "numbered_entry_lines": 0,
      "section_headers": 0,
      "probable_ocr_noise": 0.0
    },
    {
      "page_number": 14,
      "char_count": 3124,
      "line_count": 45,
      "numbered_entry_lines": 0,
      "section_headers": 0,
      "probable_ocr_noise": 0.0
    },
    {
      "page_number": 15,
      "char_count": 2743,
      "line_count": 45,
      "numbered_entry_lines": 1,
      "section_headers": 1,
      "probable_ocr_noise": 0.0
    },
    {
      "page_number": 16,
      "char_count": 2901,
      "line_count": 44,
      "numbered_entry_lines": 0,
      "section_headers": 1,
      "probable_ocr_noise": 0.0003447087211306446
    },
    {
      "page_number": 17,
      "char_count": 3171,
      "line_count": 46,
      "numbered_entry_lines": 0,
      "section_headers": 0,
      "probable_ocr_noise": 0.0
    },
    {
      "page_number": 18,
      "char_count": 2850,
      "line_count": 42,
      "numbered_entry_lines": 0,
      "section_headers": 0,
      "probable_ocr_noise": 0.0
    },
    {
      "page_number": 19,
      "char_count": 2469,
      "line_count": 38,
      "numbered_entry_lines": 0,
      "section_headers": 2,
      "probable_ocr_noise": 0.0
    },
    {
      "page_number": 20,
      "char_count": 2423,
      "line_count": 37,
      "numbered_entry_lines": 0,
      "section_headers": 3,
      "probable_ocr_noise": 0.0
    },
    {
      "page_number": 21,
      "char_count": 2398,
      "line_count": 37,
      "numbered_entry_lines": 0,
      "section_headers": 1,
      "probable_ocr_noise": 0.0
    }
  ],
  "detected_sections": [
    "AENEID: GENERAL",
    "ANCIENT AUTHORS AFTER VERGIL",
    "ANCIENT COMMENTARIES, SCHOLIA, VITAE",
    "APPENDIX VERGILIANA",
    "CHARACTERS",
    "COMPANIONS, COLLECTIONS, AND GENERAL STUDIES",
    "ECLOGUES: GENERAL",
    "ECLOGUES: INDIVIDUAL POEMS",
    "EIGHTEENTH CENTURY",
    "FURTHER BIBLIOGRAPHY",
    "GEORGICS: INDIVIDUAL POEMS",
    "HISTORY, MATERIAL CULTURE, AND LANDSCAPE",
    "NINETEENTH CENTURY",
    "PHILOSOPHY AND RELIGION",
    "RENAISSANCE AND TUDOR WRITERS",
    "STYLE, LANGUAGE, AND METER",
    "THE MIDDLE AGES",
    "TRANSLATIONS",
    "TWENTIETH CENTURY",
    "VERGIL AND AUGUSTAN WRITERS",
    "VERGIL AND EARLIER WRITERS",
    "VERGIL AND THE ARTS"
  ]
}